<?xml version="1.0" encoding="UTF-8" standalone="yes"?><imgdir name="01802000.img"><imgdir name="info"><canvas name="icon" width="32" height="30"><vector name="origin" x="0" y="30"/></canvas><canvas name="iconRaw" width="32" height="28"><vector name="origin" x="0" y="30"/></canvas><string name="name" value="赤いリボン"/><int name="tuc" value="5"/></imgdir><imgdir name="5000000"><imgdir name="stand"><canvas name="0" width="14" height="10"><vector name="origin" x="-10" y="30"/></canvas><canvas name="1" width="14" height="10"><vector name="origin" x="-10" y="30"/></canvas><canvas name="2" width="14" height="10"><vector name="origin" x="-10" y="30"/></canvas></imgdir><imgdir name="hungry"><canvas name="0" width="13" height="12"><vector name="origin" x="-23" y="10"/></canvas><canvas name="1" width="13" height="12"><vector name="origin" x="-23" y="10"/></canvas><canvas name="2" width="13" height="12"><vector name="origin" x="-23" y="10"/></canvas></imgdir><imgdir name="move"><canvas name="0" width="14" height="10"><vector name="origin" x="-9" y="30"/></canvas><canvas name="1" width="14" height="10"><vector name="origin" x="-11" y="29"/></canvas><canvas name="2" width="14" height="10"><vector name="origin" x="-12" y="30"/></canvas></imgdir><imgdir name="jump"><canvas name="0" width="14" height="10"><vector name="origin" x="-10" y="27"/></canvas></imgdir><imgdir name="rest0"><canvas name="0" width="13" height="12"><vector name="origin" x="-16" y="13"/></canvas><canvas name="1" width="14" height="10"><vector name="origin" x="-15" y="14"/></canvas><canvas name="2" width="13" height="11"><vector name="origin" x="-12" y="15"/></canvas></imgdir><imgdir name="chat"><canvas name="0" width="14" height="10"><vector name="origin" x="-10" y="30"/></canvas></imgdir><imgdir name="angry"><canvas name="0" width="14" height="13"><vector name="origin" x="-8" y="38"/></canvas></imgdir><imgdir name="rise"><canvas name="0" width="14" height="10"><vector name="origin" x="-12" y="22"/></canvas></imgdir><imgdir name="poor"><canvas name="0" width="13" height="12"><vector name="origin" x="-23" y="10"/></canvas></imgdir><imgdir name="dung"><canvas name="0" width="14" height="10"><vector name="origin" x="-10" y="29"/></canvas></imgdir><imgdir name="stretch"><canvas name="0" width="14" height="10"><vector name="origin" x="-21" y="30"/></canvas></imgdir><imgdir name="prone"><canvas name="0" width="13" height="12"><vector name="origin" x="-21" y="22"/></canvas></imgdir><imgdir name="alert"><canvas name="0" width="13" height="11"><vector name="origin" x="-10" y="35"/></canvas></imgdir><imgdir name="cry"><canvas name="0" width="13" height="11"><vector name="origin" x="-12" y="15"/></canvas></imgdir></imgdir></imgdir>